shubham/__init__.py
shubham-0.0.3.dist-info/LICENSE
shubham-0.0.3.dist-info/METADATA
shubham-0.0.3.dist-info/WHEEL
shubham-0.0.3.dist-info/top_level.txt
shubham-0.0.3.dist-info/RECORD
