Metadata-Version: 2.1
Name: shubham
Version: 0.0.3
Summary: My package that contains useful functions as well as my portfolio
Home-page: UNKNOWN
Author: Shubham Mohanty
Author-email: <whatsbehindit5@gmail.com>
License: UNKNOWN
Keywords: python,sockets
Platform: UNKNOWN
Classifier: Development Status :: 1 - Planning
Classifier: Intended Audience :: Developers
Classifier: Programming Language :: Python :: 3
Classifier: Operating System :: Unix
Classifier: Operating System :: MacOS :: MacOS X
Classifier: Operating System :: Microsoft :: Windows
License-File: LICENSE
